dtpyworker/__init__.py
dtpyworker/schedules.py
dtpyworker/task.py
dtpyworker/worker.py
dtpyworker-1.0.0.dist-info/METADATA
dtpyworker-1.0.0.dist-info/WHEEL
dtpyworker-1.0.0.dist-info/RECORD
