Metadata-Version: 2.3
Name: dtpyworker
Version: 1.0.0
Summary: A package to improved api library to have better development experience.
License: MIT
Author: Reza Shirazi
Author-email: reza@datgate.com
Requires-Python: >=3.11.9,<3.12.0
Classifier: License :: OSI Approved :: MIT License
Classifier: Programming Language :: Python :: 3
Requires-Dist: celery (>=5.4.0,<5.5.0)
Requires-Dist: celery-redbeat (>=2.3.2,<2.4.0)
Requires-Dist: dtpyredis (>=1.0.0,<1.1.0)
